parsergen/__init__.py
parsergen/lexer.py
parsergen/pyparse.py
parsergen/utils.py
parsergen-1.0.3.dist-info/METADATA
parsergen-1.0.3.dist-info/WHEEL
parsergen-1.0.3.dist-info/top_level.txt
parsergen-1.0.3.dist-info/RECORD
