Metadata-Version: 2.1
Name: parsergen
Version: 1.0.3
Summary: Python library for building Parsers and Lexers Easily
Home-page: https://github.com/Conqu3red/parsergen
Author: Conqu3red
License: UNKNOWN
Platform: UNKNOWN
Requires-Python: >=3.6
